robinhood/__init__.py
robinhood/robinhood.py
robinhood_api-0.1.4.dist-info/LICENSE
robinhood_api-0.1.4.dist-info/METADATA
robinhood_api-0.1.4.dist-info/WHEEL
robinhood_api-0.1.4.dist-info/top_level.txt
robinhood_api-0.1.4.dist-info/RECORD
