Metadata-Version: 2.1
Name: robinhood-api
Version: 0.1.4
Summary: the unofficial Robinhood API
Home-page: https://github.com/james-yun/robinhood
Author: James Yun
Author-email: jameswyun99@gmail.com
License: MIT
Classifier: Programming Language :: Python :: 3
Classifier: License :: OSI Approved :: MIT License
Classifier: Operating System :: OS Independent
Requires-Python: >=3.6
License-File: LICENSE
Requires-Dist: requests
